conib/__init__.py
conib/__main__.py
conib-0.0.8.dist-info/LICENSE
conib-0.0.8.dist-info/METADATA
conib-0.0.8.dist-info/WHEEL
conib-0.0.8.dist-info/entry_points.txt
conib-0.0.8.dist-info/top_level.txt
conib-0.0.8.dist-info/RECORD
