Metadata-Version: 2.1
Name: conib
Version: 0.0.8
Summary: Curation of Neurodegeneration in BEL (CONIB)
Home-page: https://github.com/pharmacome/conib
Author: Charles Tapley Hoyt
Author-email: cthoyt@gmail.com
Maintainer: Charles Tapley Hoyt
Maintainer-email: cthoyt@gmail.com
License: MIT License
Download-URL: https://github.com/pharmacome/conib/releases
Project-URL: Bug Tracker, https://github.com/pharmacome/conib/issues
Project-URL: Source Code, https://github.com/pharmacome/conib
Keywords: Biological Expression Language,BEL,Domain Specific Language,DSL,Systems biology,Networks biology,Drug repositioning
Platform: UNKNOWN
Classifier: Development Status :: 4 - Beta
Classifier: Environment :: Console
Classifier: Intended Audience :: Developers
Classifier: Intended Audience :: Science/Research
Classifier: Operating System :: OS Independent
Classifier: License :: OSI Approved :: MIT License
Classifier: Programming Language :: Python
Classifier: Programming Language :: Python :: 3.9
Classifier: Programming Language :: Python :: 3.8
Classifier: Programming Language :: Python :: 3.7
Classifier: Programming Language :: Python :: 3.6
Classifier: Programming Language :: Python :: 3 :: Only
Classifier: Topic :: Scientific/Engineering :: Bio-Informatics
Classifier: Topic :: Scientific/Engineering :: Chemistry
Requires-Python: >=3.6
Requires-Dist: pybel (>=0.15.0)
